Metadata-Version: 2.1
Name: odoo12-addon-sale_pricelist_technical
Version: 12.0.1.0.2
Summary: Prevent some pricelists from being selected on order and customer forms
Home-page: https://github.com/OCA/sale-workflow
Author: GRAP,Odoo Community Association (OCA)
Author-email: support@odoo-community.org
License: AGPL-3
Classifier: Programming Language :: Python
Classifier: Framework :: Odoo
Classifier: Framework :: Odoo :: 12.0
Classifier: License :: OSI Approved :: GNU Affero General Public License v3
Requires-Python: >=3.5
Requires-Dist: odoo<12.1dev,>=12.0a
